ngboost/__init__.py
ngboost/api.py
ngboost/distns/__init__.py
ngboost/distns/categorical.py
ngboost/distns/cauchy.py
ngboost/distns/distn.py
ngboost/distns/exponential.py
ngboost/distns/laplace.py
ngboost/distns/lognormal.py
ngboost/distns/multivariate_normal.py
ngboost/distns/normal.py
ngboost/distns/poisson.py
ngboost/distns/t.py
ngboost/distns/utils.py
ngboost/evaluation.py
ngboost/helpers.py
ngboost/learners.py
ngboost/manifold.py
ngboost/ngboost.py
ngboost/scores.py
ngboost_release-0.3.12.post2.dist-info/LICENSE
ngboost_release-0.3.12.post2.dist-info/WHEEL
ngboost_release-0.3.12.post2.dist-info/METADATA
ngboost_release-0.3.12.post2.dist-info/RECORD
