Metadata-Version: 2.1
Name: ngboost-release
Version: 0.3.12.post2
Summary: It is just a workaround to fix the current ngboost package issue. See: https://github.com/stanfordmlgroup/ngboost/issues/283
Home-page: https://github.com/stanfordmlgroup/ngboost
License: Apache-2.0
Author: Stanford ML Group
Author-email: avati@cs.stanford.edu
Requires-Python: >=3.6,<4.0
Classifier: License :: OSI Approved :: Apache Software License
Classifier: Operating System :: OS Independent
Classifier: Programming Language :: Python :: 3
Classifier: Programming Language :: Python :: 3.10
Classifier: Programming Language :: Python :: 3.6
Classifier: Programming Language :: Python :: 3.7
Classifier: Programming Language :: Python :: 3.8
Classifier: Programming Language :: Python :: 3.9
Requires-Dist: lifelines (>=0.25)
Requires-Dist: numpy (>=1.17)
Requires-Dist: scikit-learn (>=0.21)
Requires-Dist: scipy (>=1.3)
Requires-Dist: tqdm (>=4.3)
Project-URL: Documentation, https://stanfordmlgroup.github.io/ngboost/intro
Project-URL: Repository, https://github.com/stanfordmlgroup/ngboost
